modoboa_radicale/__init__.py
modoboa_radicale/apps.py
modoboa_radicale/factories.py
modoboa_radicale/forms.py
modoboa_radicale/handlers.py
modoboa_radicale/mocks.py
modoboa_radicale/models.py
modoboa_radicale/modo_extension.py
modoboa_radicale/serializers.py
modoboa_radicale/settings.py
modoboa_radicale/tests.py
modoboa_radicale/urls.py
modoboa_radicale/urls_api.py
modoboa_radicale/version.py
modoboa_radicale/views.py
modoboa_radicale/viewsets.py
modoboa_radicale/backends/__init__.py
modoboa_radicale/backends/caldav_.py
modoboa_radicale/locale/br/LC_MESSAGES/django.mo
modoboa_radicale/locale/br/LC_MESSAGES/django.po
modoboa_radicale/locale/cs_CZ/LC_MESSAGES/django.mo
modoboa_radicale/locale/cs_CZ/LC_MESSAGES/django.po
modoboa_radicale/locale/de/LC_MESSAGES/django.mo
modoboa_radicale/locale/de/LC_MESSAGES/django.po
modoboa_radicale/locale/en/LC_MESSAGES/django.mo
modoboa_radicale/locale/en/LC_MESSAGES/django.po
modoboa_radicale/locale/es/LC_MESSAGES/django.mo
modoboa_radicale/locale/es/LC_MESSAGES/django.po
modoboa_radicale/locale/fr/LC_MESSAGES/django.mo
modoboa_radicale/locale/fr/LC_MESSAGES/django.po
modoboa_radicale/locale/it/LC_MESSAGES/django.mo
modoboa_radicale/locale/it/LC_MESSAGES/django.po
modoboa_radicale/locale/nl_NL/LC_MESSAGES/django.mo
modoboa_radicale/locale/nl_NL/LC_MESSAGES/django.po
modoboa_radicale/locale/pt_BR/LC_MESSAGES/django.mo
modoboa_radicale/locale/pt_BR/LC_MESSAGES/django.po
modoboa_radicale/locale/pt_PT/LC_MESSAGES/django.mo
modoboa_radicale/locale/pt_PT/LC_MESSAGES/django.po
modoboa_radicale/locale/ro_RO/LC_MESSAGES/django.mo
modoboa_radicale/locale/ro_RO/LC_MESSAGES/django.po
modoboa_radicale/locale/ru/LC_MESSAGES/django.mo
modoboa_radicale/locale/ru/LC_MESSAGES/django.po
modoboa_radicale/locale/sv/LC_MESSAGES/django.mo
modoboa_radicale/locale/sv/LC_MESSAGES/django.po
modoboa_radicale/locale/zh_TW/LC_MESSAGES/django.mo
modoboa_radicale/locale/zh_TW/LC_MESSAGES/django.po
modoboa_radicale/management/__init__.py
modoboa_radicale-1.7.3.dist-info/LICENSE
modoboa_radicale-1.7.3.dist-info/METADATA
modoboa_radicale-1.7.3.dist-info/WHEEL
modoboa_radicale-1.7.3.dist-info/top_level.txt
modoboa_radicale-1.7.3.dist-info/RECORD
