Metadata-Version: 2.1
Name: modoboa-radicale
Version: 1.7.3
Summary: The Radicale frontend of Modoboa
Author-email: Antoine Nguyen <tonio@ngyn.org>
License: The MIT License (MIT)
Project-URL: Homepage, https://modoboa.org/
Project-URL: Documentation, https://modoboa.readthedocs.io/en/latest/
Project-URL: Repository, https://github.com/modoboa/modoboa-radicale
Project-URL: Changelog, https://github.com/modoboa/modoboa-radicale/blob/master/CHANGELOG.md
Project-URL: Issues, https://github.com/modoboa/modoboa-radicale/issues
Keywords: modoboa,email,radicale,calendar,caldav
Classifier: Development Status :: 5 - Production/Stable
Classifier: Environment :: Web Environment
Classifier: Framework :: Django :: 4.2
Classifier: Intended Audience :: System Administrators
Classifier: License :: OSI Approved :: ISC License (ISCL)
Classifier: Operating System :: OS Independent
Classifier: Programming Language :: Python :: 3
Classifier: Programming Language :: Python :: 3.9
Classifier: Programming Language :: Python :: 3.10
Classifier: Programming Language :: Python :: 3.11
Classifier: Programming Language :: Python :: 3.12
Classifier: Topic :: Communications :: Email
Classifier: Topic :: Internet :: WWW/HTTP
Requires-Python: >=3.9
License-File: LICENSE
Requires-Dist: drf-nested-routers
Requires-Dist: django-webpack-loader==2.0.1
Requires-Dist: caldav==1.3.9
Provides-Extra: test
Requires-Dist: factory-boy<3.4.0; extra == "test"
Requires-Dist: testfixtures==8.1.0; extra == "test"
Requires-Dist: psycopg[binary]>=3.1; extra == "test"
Requires-Dist: mysqlclient<2.2.5; extra == "test"
Requires-Dist: packaging; extra == "test"
